README.md
setup.py
virtualenv_switcher.py
virtualenv_switcher.egg-info/PKG-INFO
virtualenv_switcher.egg-info/SOURCES.txt
virtualenv_switcher.egg-info/dependency_links.txt
virtualenv_switcher.egg-info/entry_points.txt
virtualenv_switcher.egg-info/top_level.txt