Metadata-Version: 1.1
Name: virtualenv-switcher
Version: 0.1.0
Summary: Virtualenv switcher.
Home-page: https://www.github.org/kvas-it/virtualenv-switcher/
Author: UNKNOWN
Author-email: UNKNOWN
License: MIT
Keywords: virtualenv
Platform: UNKNOWN
Classifier: Development Status :: 3 - Alpha
Classifier: Intended Audience :: Developers
Classifier: License :: OSI Approved :: MIT License
Classifier: Natural Language :: English
Classifier: Programming Language :: Python :: 3
